Metadata-Version: 2.1
Name: pyamis
Version: 1.0.1
Summary: py lib for frontend framework amis which generates valid amis response with json
Home-page: https://github.com/mythmgn/pyamis
Author: Guannan Ma
Author-email: mythmgn@gmail.com
License: Apache License V2
Keywords: amis,pyamis
Platform: UNKNOWN
Classifier: Programming Language :: Python
Classifier: Programming Language :: Python :: 2
Classifier: Programming Language :: Python :: 2.7
Classifier: Programming Language :: Python :: 3
Classifier: Operating System :: OS Independent
